props2yaml/__init__.py
props2yaml/__main__.py
props2yaml/__version__.py
props2yaml/converter.py
props2yaml/main.py
props2yaml-0.1.2.dist-info/LICENSE
props2yaml-0.1.2.dist-info/METADATA
props2yaml-0.1.2.dist-info/WHEEL
props2yaml-0.1.2.dist-info/entry_points.txt
props2yaml-0.1.2.dist-info/top_level.txt
props2yaml-0.1.2.dist-info/RECORD
