Metadata-Version: 2.1
Name: props2yaml
Version: 0.1.2
Summary: Convert .properties files into .yaml
Author-email: "Jorge F. Sánchez" <props2yaml@jfsanchez.net>
License: MIT
Project-URL: Homepage, https://github.com/jfsanchez91/props2yaml
Project-URL: Bug Tracker, https://github.com/jfsanchez91/props2yaml/issues
Keywords: yaml,properties,converter
Classifier: Programming Language :: Python :: 3
Classifier: License :: OSI Approved :: MIT License
Classifier: Operating System :: OS Independent
Requires-Python: >=3.8
License-File: LICENSE
Requires-Dist: pyyaml
Provides-Extra: dev
Requires-Dist: black ; extra == 'dev'
Provides-Extra: test
Requires-Dist: pytest ; extra == 'test'
